{
  "$schema": "https://developer.microsoft.com/json-schemas/spfx-build/package-solution.schema.json",
  "solution": {
    "name": "tabs-client-side-solution",
    "id": "823e6849-e847-4002-9024-3ac5365fa923",
    "version": "2.0.0.1",
    "includeClientSideAssets": true,
    "skipFeatureDeployment": true,
    "isDomainIsolated": false,
    "developer": {
      "name": "",
      "websiteUrl": "",
      "privacyUrl": "",
      "termsOfUseUrl": "",
      "mpnId": "Undefined-1.18.1"
    },
    "metadata": {
      "shortDescription": {
        "default": "Tabs description"
      },
      "longDescription": {
        "default": "Tabs description"
      },
      "screenshotPaths": [],
      "videoUrl": "",
      "categories": []
    },
    "features": [
      {
        "title": "tabs Feature",
        "description": "The feature that activates elements of the tabs solution.",
        "id": "606da62c-c27f-4e4d-812c-4fc76abdcde0",
        "version": "1.0.0.0"
      }
    ]
  },
  "paths": {
    "zippedPackage": "solution/tabs.sppkg"
  }
}
